Metadata-Version: 2.1
Name: dinesh-search
Version: 0.0.1
Summary: Simple trimmer and space remover
Home-page: UNKNOWN
Author: Satya Venkata Dinesh Kumar Vetcha
Author-email: satyadinesh118@gmail.com
License: MIT
Keywords: Trim strip
Platform: UNKNOWN
Classifier: Development Status :: 5 - Production/Stable
Classifier: Intended Audience :: Education
Classifier: Operating System :: Microsoft :: Windows :: Windows 10
Classifier: License :: OSI Approved :: MIT License
Classifier: Programming Language :: Python :: 3
License-File: LICENSE.txt
